CHANGES.txt
CONTRIBUTORS.txt
MANIFEST.in
README.txt
setup.cfg
setup.py
GrailTact/__init__.py
GrailTact.egg-info/PKG-INFO
GrailTact.egg-info/SOURCES.txt
GrailTact.egg-info/dependency_links.txt
GrailTact.egg-info/entry_points.txt
GrailTact.egg-info/namespace_packages.txt
GrailTact.egg-info/not-zip-safe
GrailTact.egg-info/paster_plugins.txt
GrailTact.egg-info/requires.txt
GrailTact.egg-info/top_level.txt
GrailTact/GrailTact/README.txt
GrailTact/GrailTact/__init__.py
GrailTact/GrailTact/changes.txt
GrailTact/GrailTact/config.py
GrailTact/GrailTact/configure.zcml
GrailTact/GrailTact/readme.txt
GrailTact/GrailTact/browser/__init__.py
GrailTact/GrailTact/browser/configure.zcml
GrailTact/GrailTact/content/__init__.py
GrailTact/GrailTact/content/configure.zcml
GrailTact/GrailTact/content/contact.py
GrailTact/GrailTact/content/contactemailaddress.py
GrailTact/GrailTact/content/contactlandingpage.py
GrailTact/GrailTact/content/contactnetaddress.py
GrailTact/GrailTact/content/contactphonenumber.py
GrailTact/GrailTact/content/contactworkplaceandworktitle.py
GrailTact/GrailTact/interfaces/__init__.py
GrailTact/GrailTact/interfaces/contact.py
GrailTact/GrailTact/interfaces/contactemailaddress.py
GrailTact/GrailTact/interfaces/contactnetaddress.py
GrailTact/GrailTact/interfaces/contactphonenumber.py
GrailTact/GrailTact/interfaces/contactworkplaceandworktitle.py
GrailTact/GrailTact/portlets/__init__.py
GrailTact/GrailTact/portlets/configure.zcml
GrailTact/GrailTact/profiles/default/factorytool.xml
GrailTact/GrailTact/profiles/default/metadata.xml
GrailTact/GrailTact/profiles/default/portlets.xml
GrailTact/GrailTact/profiles/default/rolemap.xml
GrailTact/GrailTact/profiles/default/skins.xml
GrailTact/GrailTact/profiles/default/types.xml
GrailTact/GrailTact/profiles/default/types/Contact.xml
GrailTact/GrailTact/profiles/default/types/Contact_email_address.xml
GrailTact/GrailTact/profiles/default/types/Contact_landing_page.xml
GrailTact/GrailTact/profiles/default/types/Contact_net_address.xml
GrailTact/GrailTact/profiles/default/types/Contact_phone_number.xml
GrailTact/GrailTact/profiles/default/types/Contact_workplace_and_work_title.xml
GrailTact/GrailTact/skins/GrailTact/test.pt
GrailTact/GrailTact/tests/__init__.py
GrailTact/GrailTact/tests/base.py
