Metadata-Version: 1.0
Name: GrailTact
Version: 1.4.1
Summary: Contact database with good import/export (general connectivity)
Home-page: http://www.nidelven-it.no/d
Author: Morten W. Petersen
Author-email: morten@nidelven-it.no
License: GPL
Platform: UNKNOWN
Classifier: Framework :: Plone
Classifier: Intended Audience :: Developers
Classifier: License :: OSI Approved :: GNU General Public License (GPL)
